{
  "generated": "2026-03-23T12:43:46.063900",
  "devices": [
    {
      "id": "DXCM_G7_15DAY",
      "name": "Dexcom G7 15-Day",
      "ticker": "DXCM",
      "company": "Dexcom",
      "month": "2026-02",
      "reports": 238,
      "z_score": 1.4,
      "rate_per_m": 0.56,
      "rate_per_10k": 0.6704,
      "slope_6m": 0,
      "deaths_3mo": 0,
      "injuries_3mo": 7,
      "r_score": null,
      "signal": "NORMAL",
      "batch_warning": false
    },
    {
      "id": "DXCM_G7",
      "name": "Dexcom G7 (10-Day)",
      "ticker": "DXCM",
      "company": "Dexcom",
      "month": "2026-02",
      "reports": 15329,
      "z_score": -0.72,
      "rate_per_m": 36.21,
      "rate_per_10k": 43.1803,
      "slope_6m": 3066.57,
      "deaths_3mo": 10,
      "injuries_3mo": 1382,
      "r_score": 84.8,
      "signal": "CRITICAL",
      "batch_warning": true
    },
    {
      "id": "DXCM_G6",
      "name": "Dexcom G6",
      "ticker": "DXCM",
      "company": "Dexcom",
      "month": "2026-02",
      "reports": 4339,
      "z_score": -1.83,
      "rate_per_m": 10.25,
      "rate_per_10k": 12.2225,
      "slope_6m": -1102.77,
      "deaths_3mo": 2,
      "injuries_3mo": 275,
      "r_score": 12.2,
      "signal": "NORMAL",
      "batch_warning": true
    },
    {
      "id": "DXCM_STELO",
      "name": "Dexcom Stelo",
      "ticker": "DXCM",
      "company": "Dexcom",
      "month": "2026-02",
      "reports": 119,
      "z_score": -0.0,
      "rate_per_m": 0.28,
      "rate_per_10k": 0.3352,
      "slope_6m": -1.8,
      "deaths_3mo": 0,
      "injuries_3mo": 27,
      "r_score": 0.8,
      "signal": "NORMAL",
      "batch_warning": false
    },
    {
      "id": "DXCM_ONE",
      "name": "Dexcom ONE/ONE+",
      "ticker": "DXCM",
      "company": "Dexcom",
      "month": "2026-02",
      "reports": 10,
      "z_score": -1.8,
      "rate_per_m": 0.02,
      "rate_per_10k": 0.0282,
      "slope_6m": -2.4,
      "deaths_3mo": 0,
      "injuries_3mo": 0,
      "r_score": 12.0,
      "signal": "NORMAL",
      "batch_warning": true
    },
    {
      "id": "DXCM_ALL",
      "name": "All Dexcom (combined)",
      "ticker": "DXCM",
      "company": "Dexcom",
      "month": "2026-02",
      "reports": 19921,
      "z_score": -0.92,
      "rate_per_m": 47.06,
      "rate_per_10k": 56.1155,
      "slope_6m": 1995.94,
      "deaths_3mo": 12,
      "injuries_3mo": 1671,
      "r_score": 72.1,
      "signal": "CRITICAL",
      "batch_warning": true
    },
    {
      "id": "PODD_OP5",
      "name": "Omnipod 5",
      "ticker": "PODD",
      "company": "Insulet",
      "month": "2026-02",
      "reports": 5652,
      "z_score": 0.78,
      "rate_per_m": 20.93,
      "rate_per_10k": 91.1613,
      "slope_6m": -223.54,
      "deaths_3mo": 9,
      "injuries_3mo": 1527,
      "r_score": 5.2,
      "signal": "NORMAL",
      "batch_warning": true
    },
    {
      "id": "PODD_DASH",
      "name": "Omnipod DASH",
      "ticker": "PODD",
      "company": "Insulet",
      "month": "2026-02",
      "reports": 449,
      "z_score": -0.93,
      "rate_per_m": 1.66,
      "rate_per_10k": 7.2419,
      "slope_6m": -67.91,
      "deaths_3mo": 1,
      "injuries_3mo": 72,
      "r_score": 6.2,
      "signal": "NORMAL",
      "batch_warning": true
    },
    {
      "id": "PODD_ALL",
      "name": "All Omnipod (combined)",
      "ticker": "PODD",
      "company": "Insulet",
      "month": "2026-02",
      "reports": 6129,
      "z_score": 0.55,
      "rate_per_m": 22.7,
      "rate_per_10k": 98.8548,
      "slope_6m": -303.2,
      "deaths_3mo": 10,
      "injuries_3mo": 1605,
      "r_score": 3.7,
      "signal": "NORMAL",
      "batch_warning": true
    },
    {
      "id": "TNDM_TSLIM",
      "name": "Tandem t:slim X2",
      "ticker": "TNDM",
      "company": "Tandem",
      "month": "2026-02",
      "reports": 15823,
      "z_score": -0.6,
      "rate_per_m": 182.57,
      "rate_per_10k": 363.7471,
      "slope_6m": -307.86,
      "deaths_3mo": 11,
      "injuries_3mo": 4758,
      "r_score": 10.5,
      "signal": "NORMAL",
      "batch_warning": false
    },
    {
      "id": "TNDM_MOBI",
      "name": "Tandem Mobi",
      "ticker": "TNDM",
      "company": "Tandem",
      "month": "2026-02",
      "reports": 3095,
      "z_score": -1.02,
      "rate_per_m": 35.71,
      "rate_per_10k": 71.1494,
      "slope_6m": -222.94,
      "deaths_3mo": 0,
      "injuries_3mo": 1633,
      "r_score": 6.8,
      "signal": "NORMAL",
      "batch_warning": false
    },
    {
      "id": "TNDM_ALL",
      "name": "All Tandem (combined)",
      "ticker": "TNDM",
      "company": "Tandem",
      "month": "2026-02",
      "reports": 3104,
      "z_score": -1.02,
      "rate_per_m": 35.82,
      "rate_per_10k": 71.3563,
      "slope_6m": -223.57,
      "deaths_3mo": 1,
      "injuries_3mo": 1646,
      "r_score": 6.8,
      "signal": "NORMAL",
      "batch_warning": false
    },
    {
      "id": "ABT_LIBRE3",
      "name": "FreeStyle Libre 3/3 Plus",
      "ticker": "ABT_LIBRE",
      "company": "Abbott",
      "month": "2026-02",
      "reports": 2316,
      "z_score": 0.25,
      "rate_per_m": 3.16,
      "rate_per_10k": 2.7247,
      "slope_6m": 448.03,
      "deaths_3mo": 39,
      "injuries_3mo": 1867,
      "r_score": 81.7,
      "signal": "CRITICAL",
      "batch_warning": false
    },
    {
      "id": "ABT_LIBRE2",
      "name": "FreeStyle Libre 2",
      "ticker": "ABT_LIBRE",
      "company": "Abbott",
      "month": "2026-02",
      "reports": 1686,
      "z_score": -0.45,
      "rate_per_m": 2.3,
      "rate_per_10k": 1.9835,
      "slope_6m": -124.43,
      "deaths_3mo": 3,
      "injuries_3mo": 865,
      "r_score": 3.0,
      "signal": "NORMAL",
      "batch_warning": false
    },
    {
      "id": "ABT_LIBRE_ALL",
      "name": "All FreeStyle Libre (combined)",
      "ticker": "ABT_LIBRE",
      "company": "Abbott",
      "month": "2026-02",
      "reports": 4129,
      "z_score": 0.01,
      "rate_per_m": 5.63,
      "rate_per_10k": 4.8576,
      "slope_6m": 330.06,
      "deaths_3mo": 43,
      "injuries_3mo": 2850,
      "r_score": 76.1,
      "signal": "CRITICAL",
      "batch_warning": false
    },
    {
      "id": "SQEL_TWIIST",
      "name": "twiist AID System",
      "ticker": "SQEL",
      "company": "Sequel Med Tech",
      "month": "2026-02",
      "reports": 11,
      "z_score": 1.93,
      "rate_per_m": null,
      "rate_per_10k": null,
      "slope_6m": 1.91,
      "deaths_3mo": 0,
      "injuries_3mo": 19,
      "r_score": 72.9,
      "signal": "CRITICAL",
      "batch_warning": false
    }
  ]
}